Metadata-Version: 2.1
Name: odoo12-addon-l10n-it-website-portal-fatturapa
Version: 12.0.1.3.0
Summary: Add fatturapa fields and checks in frontend user's details
Home-page: https://github.com/OCA/l10n-italy/tree/12.0/l10n_it_website_portal_fatturapa
Author: Odoo Community Association (OCA)
Author-email: support@odoo-community.org
License: AGPL-3
Platform: UNKNOWN
Classifier: Programming Language :: Python
Classifier: Framework :: Odoo
Classifier: License :: OSI Approved :: GNU Affero General Public License v3
Requires-Python: >=3.5
Requires-Dist: odoo12-addon-l10n-it-fatturapa
Requires-Dist: odoo12-addon-l10n-it-website-portal-fiscalcode
Requires-Dist: odoo12-addon-l10n-it-website-portal-ipa
Requires-Dist: odoo (<12.1dev,>=12.0a)
